<?xml version="1.0" encoding="utf-8"?>
<TM>
  <TM_MAIN>
    <SL_NO>1</SL_NO>
    <TM_FOR>T</TM_FOR>
    <CURRENCY_CODE>001</CURRENCY_CODE>
    <COUNTRY_CODE>1100</COUNTRY_CODE>
    <PURPOSE_CODE>1130</PURPOSE_CODE>
    <BENEFICIARY_DETAILS>NA</BENEFICIARY_DETAILS>
    <APPLICANT_NAME>HIRA RANI SAHA CHOWDHURY</APPLICANT_NAME>
    <APPLICANT_ADDRESS>CHOKPUR,SINGRA,.</APPLICANT_ADDRESS>
    <EFFECTED_REMITTANCE>150</EFFECTED_REMITTANCE>
    <FX_MANUAL_PARA>CHAPTER-10</FX_MANUAL_PARA>
    <BB_APPROVAL_NO>NA</BB_APPROVAL_NO>
    <APPROVAL_DATE>NA</APPROVAL_DATE>
    <CATEGORY_CODE>42</CATEGORY_CODE>
    <TM_DATE>2021-09-07</TM_DATE>
    <COMPANY_TYPE_ID>3</COMPANY_TYPE_ID>
    <MOP_CASH>150.00</MOP_CASH>
    <MOP_TC>NA</MOP_TC>
    <MOP_CARD>NA</MOP_CARD>
    <MOP_FDD>NA</MOP_FDD>
    <MOP_MT>NA</MOP_MT>
    <MOP_OTHER>NA</MOP_OTHER>
    <SFC_BANK>150.00</SFC_BANK>
    <SFC_FC_AC>NA</SFC_FC_AC>
    <SFC_ERQ>NA</SFC_ERQ>
    <SFC_OTHER>NA</SFC_OTHER>
    <AMOUNT_IN_BDT>13050.0000</AMOUNT_IN_BDT>
    <CONTACT_NO>01712111092</CONTACT_NO>
    <BANK_REFERENCE>JBL/RAJSHAHI CORPORATE/PE/20210907/470</BANK_REFERENCE>
    <PASSPORT>
      <SL_NO>1</SL_NO>
      <PASSPORT_NO>BQ0591305</PASSPORT_NO>
      <CITIZEN_NAME>HIRA RANI SAHA CHOWDHURY</CITIZEN_NAME>
      <ADDRESS>CHOKPUR,SINGRA,.</ADDRESS>
      <PASSPORT_DATE>2017-10-16</PASSPORT_DATE>
      <PASSPORT_ISSUE_PLACE>NATORE</PASSPORT_ISSUE_PLACE>
      <PASSPORT_RENEWAL_DATE>NA</PASSPORT_RENEWAL_DATE>
    </PASSPORT>
  </TM_MAIN>
  <TM_MAIN>
    <SL_NO>2</SL_NO>
    <TM_FOR>T</TM_FOR>
    <CURRENCY_CODE>001</CURRENCY_CODE>
    <COUNTRY_CODE>1100</COUNTRY_CODE>
    <PURPOSE_CODE>1130</PURPOSE_CODE>
    <BENEFICIARY_DETAILS>NA</BENEFICIARY_DETAILS>
    <APPLICANT_NAME>SHIKHA RANI GHOSH  </APPLICANT_NAME>
    <APPLICANT_ADDRESS>BARAPANGASHI,ULLAPARA,SIRAJGANJ.</APPLICANT_ADDRESS>
    <EFFECTED_REMITTANCE>150</EFFECTED_REMITTANCE>
    <FX_MANUAL_PARA>CHAPTER-10</FX_MANUAL_PARA>
    <BB_APPROVAL_NO>NA</BB_APPROVAL_NO>
    <APPROVAL_DATE>NA</APPROVAL_DATE>
    <CATEGORY_CODE>42</CATEGORY_CODE>
    <TM_DATE>2021-09-07</TM_DATE>
    <COMPANY_TYPE_ID>3</COMPANY_TYPE_ID>
    <MOP_CASH>150.00</MOP_CASH>
    <MOP_TC>NA</MOP_TC>
    <MOP_CARD>NA</MOP_CARD>
    <MOP_FDD>NA</MOP_FDD>
    <MOP_MT>NA</MOP_MT>
    <MOP_OTHER>NA</MOP_OTHER>
    <SFC_BANK>150.00</SFC_BANK>
    <SFC_FC_AC>NA</SFC_FC_AC>
    <SFC_ERQ>NA</SFC_ERQ>
    <SFC_OTHER>NA</SFC_OTHER>
    <AMOUNT_IN_BDT>13050.0000</AMOUNT_IN_BDT>
    <CONTACT_NO>01723112016</CONTACT_NO>
    <BANK_REFERENCE>JBL/RAJSHAHI CORPORATE/PE/20210907/471</BANK_REFERENCE>
    <PASSPORT>
      <SL_NO>1</SL_NO>
      <PASSPORT_NO>EH0954335</PASSPORT_NO>
      <CITIZEN_NAME>SHIKHA RANI GHOSH  </CITIZEN_NAME>
      <ADDRESS>BARAPANGASHI,ULLAPARA,SIRAJGANJ.</ADDRESS>
      <PASSPORT_DATE>2021-04-27</PASSPORT_DATE>
      <PASSPORT_ISSUE_PLACE>SIRAJGANJ</PASSPORT_ISSUE_PLACE>
      <PASSPORT_RENEWAL_DATE>NA</PASSPORT_RENEWAL_DATE>
    </PASSPORT>
  </TM_MAIN>
  <TM_MAIN>
    <SL_NO>3</SL_NO>
    <TM_FOR>T</TM_FOR>
    <CURRENCY_CODE>001</CURRENCY_CODE>
    <COUNTRY_CODE>1100</COUNTRY_CODE>
    <PURPOSE_CODE>1130</PURPOSE_CODE>
    <BENEFICIARY_DETAILS>NA</BENEFICIARY_DETAILS>
    <APPLICANT_NAME>MD IMRAN ALI</APPLICANT_NAME>
    <APPLICANT_ADDRESS>CHAK BYADDO NATH,NATORE SADAR,NATORE.</APPLICANT_ADDRESS>
    <EFFECTED_REMITTANCE>150</EFFECTED_REMITTANCE>
    <FX_MANUAL_PARA>CHAPTER-10</FX_MANUAL_PARA>
    <BB_APPROVAL_NO>NA</BB_APPROVAL_NO>
    <APPROVAL_DATE>NA</APPROVAL_DATE>
    <CATEGORY_CODE>42</CATEGORY_CODE>
    <TM_DATE>2021-09-07</TM_DATE>
    <COMPANY_TYPE_ID>3</COMPANY_TYPE_ID>
    <MOP_CASH>150.00</MOP_CASH>
    <MOP_TC>NA</MOP_TC>
    <MOP_CARD>NA</MOP_CARD>
    <MOP_FDD>NA</MOP_FDD>
    <MOP_MT>NA</MOP_MT>
    <MOP_OTHER>NA</MOP_OTHER>
    <SFC_BANK>150.00</SFC_BANK>
    <SFC_FC_AC>NA</SFC_FC_AC>
    <SFC_ERQ>NA</SFC_ERQ>
    <SFC_OTHER>NA</SFC_OTHER>
    <AMOUNT_IN_BDT>13050.0000</AMOUNT_IN_BDT>
    <CONTACT_NO>01718056266</CONTACT_NO>
    <BANK_REFERENCE>JBL/RAJSHAHI CORPORATE/PE/20210907/472</BANK_REFERENCE>
    <PASSPORT>
      <SL_NO>1</SL_NO>
      <PASSPORT_NO>BR0356077</PASSPORT_NO>
      <CITIZEN_NAME>MD IMRAN ALI</CITIZEN_NAME>
      <ADDRESS>CHAK BYADDO NATH,NATORE SADAR,NATORE.</ADDRESS>
      <PASSPORT_DATE>2018-01-01</PASSPORT_DATE>
      <PASSPORT_ISSUE_PLACE>NATORE.</PASSPORT_ISSUE_PLACE>
      <PASSPORT_RENEWAL_DATE>NA</PASSPORT_RENEWAL_DATE>
    </PASSPORT>
  </TM_MAIN>
  <TM_MAIN>
    <SL_NO>4</SL_NO>
    <TM_FOR>T</TM_FOR>
    <CURRENCY_CODE>001</CURRENCY_CODE>
    <COUNTRY_CODE>1100</COUNTRY_CODE>
    <PURPOSE_CODE>1130</PURPOSE_CODE>
    <BENEFICIARY_DETAILS>NA</BENEFICIARY_DETAILS>
    <APPLICANT_NAME>MST SENAM BEGUM</APPLICANT_NAME>
    <APPLICANT_ADDRESS>CHAK BYADDO NATH,NATORE SADAR,NATORE</APPLICANT_ADDRESS>
    <EFFECTED_REMITTANCE>150</EFFECTED_REMITTANCE>
    <FX_MANUAL_PARA>CHAPTER-10</FX_MANUAL_PARA>
    <BB_APPROVAL_NO>NA</BB_APPROVAL_NO>
    <APPROVAL_DATE>NA</APPROVAL_DATE>
    <CATEGORY_CODE>42</CATEGORY_CODE>
    <TM_DATE>2021-09-07</TM_DATE>
    <COMPANY_TYPE_ID>3</COMPANY_TYPE_ID>
    <MOP_CASH>150.00</MOP_CASH>
    <MOP_TC>NA</MOP_TC>
    <MOP_CARD>NA</MOP_CARD>
    <MOP_FDD>NA</MOP_FDD>
    <MOP_MT>NA</MOP_MT>
    <MOP_OTHER>NA</MOP_OTHER>
    <SFC_BANK>150.00</SFC_BANK>
    <SFC_FC_AC>NA</SFC_FC_AC>
    <SFC_ERQ>NA</SFC_ERQ>
    <SFC_OTHER>NA</SFC_OTHER>
    <AMOUNT_IN_BDT>13050.0000</AMOUNT_IN_BDT>
    <CONTACT_NO>01675074865</CONTACT_NO>
    <BANK_REFERENCE>JBL/RAJSHAHI CORPORATE/PE/20210907/473</BANK_REFERENCE>
    <PASSPORT>
      <SL_NO>1</SL_NO>
      <PASSPORT_NO>BR0356268</PASSPORT_NO>
      <CITIZEN_NAME>MST SENAM BEGUM</CITIZEN_NAME>
      <ADDRESS>CHAK BYADDO NATH,NATORE SADAR,NATORE</ADDRESS>
      <PASSPORT_DATE>2018-01-01</PASSPORT_DATE>
      <PASSPORT_ISSUE_PLACE>NATORE</PASSPORT_ISSUE_PLACE>
      <PASSPORT_RENEWAL_DATE>NA</PASSPORT_RENEWAL_DATE>
    </PASSPORT>
  </TM_MAIN>
  <TM_MAIN>
    <SL_NO>5</SL_NO>
    <TM_FOR>T</TM_FOR>
    <CURRENCY_CODE>001</CURRENCY_CODE>
    <COUNTRY_CODE>1100</COUNTRY_CODE>
    <PURPOSE_CODE>1130</PURPOSE_CODE>
    <BENEFICIARY_DETAILS>NA</BENEFICIARY_DETAILS>
    <APPLICANT_NAME>MD MESBAHUL HOQUE</APPLICANT_NAME>
    <APPLICANT_ADDRESS>ALAMPUR,GOMOSTAPUR,CHAPAINAWABGANJ.</APPLICANT_ADDRESS>
    <EFFECTED_REMITTANCE>150</EFFECTED_REMITTANCE>
    <FX_MANUAL_PARA>CHAPTER-10</FX_MANUAL_PARA>
    <BB_APPROVAL_NO>NA</BB_APPROVAL_NO>
    <APPROVAL_DATE>NA</APPROVAL_DATE>
    <CATEGORY_CODE>42</CATEGORY_CODE>
    <TM_DATE>2021-09-07</TM_DATE>
    <COMPANY_TYPE_ID>3</COMPANY_TYPE_ID>
    <MOP_CASH>150.00</MOP_CASH>
    <MOP_TC>NA</MOP_TC>
    <MOP_CARD>NA</MOP_CARD>
    <MOP_FDD>NA</MOP_FDD>
    <MOP_MT>NA</MOP_MT>
    <MOP_OTHER>NA</MOP_OTHER>
    <SFC_BANK>150.00</SFC_BANK>
    <SFC_FC_AC>NA</SFC_FC_AC>
    <SFC_ERQ>NA</SFC_ERQ>
    <SFC_OTHER>NA</SFC_OTHER>
    <AMOUNT_IN_BDT>13050.0000</AMOUNT_IN_BDT>
    <CONTACT_NO>01715138363</CONTACT_NO>
    <BANK_REFERENCE>JBL/RAJSHAHI CORPORATE/PE/20210907/474</BANK_REFERENCE>
    <PASSPORT>
      <SL_NO>1</SL_NO>
      <PASSPORT_NO>BP0550276</PASSPORT_NO>
      <CITIZEN_NAME>MD MESBAHUL HOQUE</CITIZEN_NAME>
      <ADDRESS>ALAMPUR,GOMOSTAPUR,CHAPAINAWABGANJ.</ADDRESS>
      <PASSPORT_DATE>2017-06-28</PASSPORT_DATE>
      <PASSPORT_ISSUE_PLACE>CHAPAINAWABGANJ</PASSPORT_ISSUE_PLACE>
      <PASSPORT_RENEWAL_DATE>NA</PASSPORT_RENEWAL_DATE>
    </PASSPORT>
  </TM_MAIN>
  <TM_MAIN>
    <SL_NO>6</SL_NO>
    <TM_FOR>T</TM_FOR>
    <CURRENCY_CODE>001</CURRENCY_CODE>
    <COUNTRY_CODE>1100</COUNTRY_CODE>
    <PURPOSE_CODE>1130</PURPOSE_CODE>
    <BENEFICIARY_DETAILS>NA</BENEFICIARY_DETAILS>
    <APPLICANT_NAME>M SADRUL ISLAM  </APPLICANT_NAME>
    <APPLICANT_ADDRESS>MIRZAPUR,SHIBGANJ,CHAPAINAWABGANJ</APPLICANT_ADDRESS>
    <EFFECTED_REMITTANCE>150</EFFECTED_REMITTANCE>
    <FX_MANUAL_PARA>CHAPTER-10</FX_MANUAL_PARA>
    <BB_APPROVAL_NO>NA</BB_APPROVAL_NO>
    <APPROVAL_DATE>NA</APPROVAL_DATE>
    <CATEGORY_CODE>42</CATEGORY_CODE>
    <TM_DATE>2021-09-07</TM_DATE>
    <COMPANY_TYPE_ID>3</COMPANY_TYPE_ID>
    <MOP_CASH>150.00</MOP_CASH>
    <MOP_TC>NA</MOP_TC>
    <MOP_CARD>NA</MOP_CARD>
    <MOP_FDD>NA</MOP_FDD>
    <MOP_MT>NA</MOP_MT>
    <MOP_OTHER>NA</MOP_OTHER>
    <SFC_BANK>150.00</SFC_BANK>
    <SFC_FC_AC>NA</SFC_FC_AC>
    <SFC_ERQ>NA</SFC_ERQ>
    <SFC_OTHER>NA</SFC_OTHER>
    <AMOUNT_IN_BDT>13050.0000</AMOUNT_IN_BDT>
    <CONTACT_NO>01723665485</CONTACT_NO>
    <BANK_REFERENCE>JBL/RAJSHAHI CORPORATE/PE/20210907/475</BANK_REFERENCE>
    <PASSPORT>
      <SL_NO>1</SL_NO>
      <PASSPORT_NO>BQ0050737</PASSPORT_NO>
      <CITIZEN_NAME>M SADRUL ISLAM  </CITIZEN_NAME>
      <ADDRESS>MIRZAPUR,SHIBGANJ,CHAPAINAWABGANJ</ADDRESS>
      <PASSPORT_DATE>2017-08-23</PASSPORT_DATE>
      <PASSPORT_ISSUE_PLACE>CHAPAINAWABGANJ</PASSPORT_ISSUE_PLACE>
      <PASSPORT_RENEWAL_DATE>NA</PASSPORT_RENEWAL_DATE>
    </PASSPORT>
  </TM_MAIN>
  <TM_MAIN>
    <SL_NO>7</SL_NO>
    <TM_FOR>T</TM_FOR>
    <CURRENCY_CODE>001</CURRENCY_CODE>
    <COUNTRY_CODE>1100</COUNTRY_CODE>
    <PURPOSE_CODE>1130</PURPOSE_CODE>
    <BENEFICIARY_DETAILS>NA</BENEFICIARY_DETAILS>
    <APPLICANT_NAME>MST RUPALY KHATUN  </APPLICANT_NAME>
    <APPLICANT_ADDRESS>MIRZAPUR,SHIBGANJ,CHAPAINAWABGANJ</APPLICANT_ADDRESS>
    <EFFECTED_REMITTANCE>150</EFFECTED_REMITTANCE>
    <FX_MANUAL_PARA>CHAPTER-10</FX_MANUAL_PARA>
    <BB_APPROVAL_NO>NA</BB_APPROVAL_NO>
    <APPROVAL_DATE>NA</APPROVAL_DATE>
    <CATEGORY_CODE>42</CATEGORY_CODE>
    <TM_DATE>2021-09-07</TM_DATE>
    <COMPANY_TYPE_ID>3</COMPANY_TYPE_ID>
    <MOP_CASH>150.00</MOP_CASH>
    <MOP_TC>NA</MOP_TC>
    <MOP_CARD>NA</MOP_CARD>
    <MOP_FDD>NA</MOP_FDD>
    <MOP_MT>NA</MOP_MT>
    <MOP_OTHER>NA</MOP_OTHER>
    <SFC_BANK>150.00</SFC_BANK>
    <SFC_FC_AC>NA</SFC_FC_AC>
    <SFC_ERQ>NA</SFC_ERQ>
    <SFC_OTHER>NA</SFC_OTHER>
    <AMOUNT_IN_BDT>13050.0000</AMOUNT_IN_BDT>
    <CONTACT_NO>01771899868</CONTACT_NO>
    <BANK_REFERENCE>JBL/RAJSHAHI CORPORATE/PE/20210907/476</BANK_REFERENCE>
    <PASSPORT>
      <SL_NO>1</SL_NO>
      <PASSPORT_NO>BR0227165</PASSPORT_NO>
      <CITIZEN_NAME>MST RUPALY KHATUN  </CITIZEN_NAME>
      <ADDRESS>MIRZAPUR,SHIBGANJ,CHAPAINAWABGANJ</ADDRESS>
      <PASSPORT_DATE>2017-12-18</PASSPORT_DATE>
      <PASSPORT_ISSUE_PLACE>CHAPAINAWABGANJ</PASSPORT_ISSUE_PLACE>
      <PASSPORT_RENEWAL_DATE>NA</PASSPORT_RENEWAL_DATE>
    </PASSPORT>
  </TM_MAIN>
</TM>
